<?xml version="1.0" encoding="UTF-8"?>
<CUT_SCHEME>
  <Versions BretonTouch="1.32.0+767" XmlCam3="1.2.1.0" Aom3.API="4.21.1.0" CSE="1.32.0+767" CUT_SCHEME_VERSION="3.0.0.0" />
  <CutSchemeGuid SLAB00000000046963="c9b1d0a5-2190-4714-909d-d79c4873ef07">
    <T_PARAMETERS Guid="87c4e177-0000-0000-0000-000000000000" />
  </CutSchemeGuid>
  <Slab Id="153156" Code="SLAB00000000046963" Length="3129.28051757813" Width="1674.14196777344" Thickness="20" ThicknessId="576" MaterialId="903">
    <Tool IdTool="170">
      <DiskDiameter>405.267</DiskDiameter>
      <DiskThickness>3.8</DiskThickness>
      <DiskGroove>92.2326909610804</DiskGroove>
    </Tool>
    <Zone>
      <Attributes />
      <MatrixRT m00="1" m01="0" m02="100.000000495565" m10="0" m11="1" m12="46.463768115942" m20="0" m21="0" m22="1" />
      <Path Type="" Mode="EN_PATH_MODE_UNKNOW">
        <Attributes>
          <__INTERNAL_NAME_ value="INST_992655" />
        </Attributes>
        <Segment X1="3129.28041159364" Y1="9.9475983006414E-14" X2="3129.28041159364" Y2="1674.14192579551" />
        <Segment X1="3129.28041159364" Y1="1674.14192579551" X2="123.28669842343" Y2="1632.05099865661" />
        <Segment X1="123.28669842343" Y1="1632.05099865661" X2="110.533474772219" Y2="1144.87785518032" />
        <Segment X1="110.533474772219" Y1="1144.87785518032" X2="0" Y2="100.158238784837" />
        <Segment X1="0" Y1="100.158238784837" X2="105.166150724078" Y2="0" />
        <Segment X1="105.166150724078" Y1="0" X2="3129.28041159364" Y2="9.9475983006414E-14" />
      </Path>
    </Zone>
    <Group Id="385710" Code="GR_0114">
      <Piece Id="662612" Code="_SP00023679_592" Type="0">
        <Zone>
          <MatrixRT m00="1" m01="0" m02="835.200970434782" m10="0" m11="1" m12="486.279190668895" m20="0" m21="0" m22="1" />
          <Path>
            <Attributes>
              <SideDirection value="0" />
              <SideDirection value="0" />
              <SideDirection value="0" />
              <SideDirection value="0" />
              <Type value="20" />
              <Depth value="21.7" />
              <SideInclination value="0" />
              <ToolType value="0" />
              <IsHole value="0" />
            </Attributes>
            <Segment X1="0" Y1="0" X2="1110" Y2="0" />
            <Segment X1="1110" Y1="0" X2="1110" Y2="1110" />
            <Segment X1="1110" Y1="1110" X2="0" Y2="1110" />
            <Segment X1="0" Y1="1110" X2="0" Y2="0" />
          </Path>
        </Zone>
        <Path>
          <Attributes>
            <Extreme1 value="1" />
            <Extreme2 value="1" />
            <ExpModule value="1.9" />
            <ToolType value="0" />
            <ToolNumber value="1" />
            <ToolId value="170" />
            <OrgPolygon value="1" />
            <OrgSide value="1" />
            <CutIncl value="0" />
            <SideInclination value="0" />
            <ToolInclination value="0" />
            <SideDirection value="0" />
            <Type value="276" />
            <Depth value="21.7" />
            <IsHole value="0" />
          </Attributes>
          <Segment X1="-2.9" Y1="-1.9" X2="1112.9" Y2="-1.9" />
        </Path>
        <Path>
          <Attributes>
            <Extreme1 value="1" />
            <Extreme2 value="1" />
            <ExpModule value="1.9" />
            <ToolType value="0" />
            <ToolNumber value="1" />
            <ToolId value="170" />
            <OrgPolygon value="1" />
            <OrgSide value="2" />
            <CutIncl value="0" />
            <SideInclination value="0" />
            <ToolInclination value="0" />
            <SideDirection value="0" />
            <Type value="276" />
            <Depth value="21.7" />
            <IsHole value="0" />
          </Attributes>
          <Segment X1="1111.9" Y1="-2.9" X2="1111.9" Y2="1112.9" />
        </Path>
        <Path>
          <Attributes>
            <Extreme1 value="1" />
            <Extreme2 value="1" />
            <ExpModule value="1.9" />
            <ToolType value="0" />
            <ToolNumber value="1" />
            <ToolId value="170" />
            <OrgPolygon value="1" />
            <OrgSide value="3" />
            <CutIncl value="0" />
            <SideInclination value="0" />
            <ToolInclination value="0" />
            <SideDirection value="0" />
            <Type value="276" />
            <Depth value="21.7" />
            <IsHole value="0" />
          </Attributes>
          <Segment X1="1112.9" Y1="1111.9" X2="-2.9" Y2="1111.9" />
        </Path>
        <Path>
          <Attributes>
            <Extreme1 value="1" />
            <Extreme2 value="1" />
            <ExpModule value="1.9" />
            <ToolType value="0" />
            <ToolNumber value="1" />
            <ToolId value="170" />
            <OrgPolygon value="1" />
            <OrgSide value="4" />
            <CutIncl value="0" />
            <SideInclination value="0" />
            <ToolInclination value="0" />
            <SideDirection value="0" />
            <Type value="276" />
            <Depth value="21.7" />
            <IsHole value="0" />
          </Attributes>
          <Segment X1="-1.9" Y1="1112.9" X2="-1.9" Y2="-2.9" />
        </Path>
      </Piece>
    </Group>
    <Group Id="385711" Code="GR_0115">
      <Piece Id="662613" Code="_SP00023679_593" Type="0">
        <Zone>
          <MatrixRT m00="1" m01="0" m02="1949.00097043478" m10="0" m11="1" m12="486.279190668895" m20="0" m21="0" m22="1" />
          <Path>
            <Attributes>
              <SideDirection value="0" />
              <SideDirection value="0" />
              <SideDirection value="0" />
              <SideDirection value="0" />
              <Type value="20" />
              <Depth value="21.7" />
              <SideInclination value="0" />
              <ToolType value="0" />
              <IsHole value="0" />
            </Attributes>
            <Segment X1="0" Y1="0" X2="1110" Y2="0" />
            <Segment X1="1110" Y1="0" X2="1110" Y2="1110" />
            <Segment X1="1110" Y1="1110" X2="0" Y2="1110" />
            <Segment X1="0" Y1="1110" X2="0" Y2="0" />
          </Path>
        </Zone>
        <Path>
          <Attributes>
            <Extreme1 value="1" />
            <Extreme2 value="1" />
            <ExpModule value="1.9" />
            <ToolType value="0" />
            <ToolNumber value="1" />
            <ToolId value="170" />
            <OrgPolygon value="1" />
            <OrgSide value="1" />
            <CutIncl value="0" />
            <SideInclination value="0" />
            <ToolInclination value="0" />
            <SideDirection value="0" />
            <Type value="276" />
            <Depth value="21.7" />
            <IsHole value="0" />
          </Attributes>
          <Segment X1="-2.9" Y1="-1.9" X2="1112.9" Y2="-1.9" />
        </Path>
        <Path>
          <Attributes>
            <Extreme1 value="1" />
            <Extreme2 value="1" />
            <ExpModule value="1.9" />
            <ToolType value="0" />
            <ToolNumber value="1" />
            <ToolId value="170" />
            <OrgPolygon value="1" />
            <OrgSide value="2" />
            <CutIncl value="0" />
            <SideInclination value="0" />
            <ToolInclination value="0" />
            <SideDirection value="0" />
            <Type value="276" />
            <Depth value="21.7" />
            <IsHole value="0" />
          </Attributes>
          <Segment X1="1111.9" Y1="-2.9" X2="1111.9" Y2="1112.9" />
        </Path>
        <Path>
          <Attributes>
            <Extreme1 value="1" />
            <Extreme2 value="1" />
            <ExpModule value="1.9" />
            <ToolType value="0" />
            <ToolNumber value="1" />
            <ToolId value="170" />
            <OrgPolygon value="1" />
            <OrgSide value="3" />
            <CutIncl value="0" />
            <SideInclination value="0" />
            <ToolInclination value="0" />
            <SideDirection value="0" />
            <Type value="276" />
            <Depth value="21.7" />
            <IsHole value="0" />
          </Attributes>
          <Segment X1="1112.9" Y1="1111.9" X2="-2.9" Y2="1111.9" />
        </Path>
        <Path>
          <Attributes>
            <Extreme1 value="1" />
            <Extreme2 value="1" />
            <ExpModule value="1.9" />
            <ToolType value="0" />
            <ToolNumber value="1" />
            <ToolId value="170" />
            <OrgPolygon value="1" />
            <OrgSide value="4" />
            <CutIncl value="0" />
            <SideInclination value="0" />
            <ToolInclination value="0" />
            <SideDirection value="0" />
            <Type value="276" />
            <Depth value="21.7" />
            <IsHole value="0" />
          </Attributes>
          <Segment X1="-1.9" Y1="1112.9" X2="-1.9" Y2="-2.9" />
        </Path>
      </Piece>
    </Group>
    <Group Id="385712" Code="GR_0116">
      <Piece Id="662614" Code="_SP00023518_594" Type="0">
        <Zone>
          <MatrixRT m00="1" m01="0" m02="2483.59952347826" m10="0" m11="1" m12="61.216397625416" m20="0" m21="0" m22="1" />
          <Path>
            <Attributes>
              <SideDirection value="0" />
              <SideDirection value="0" />
              <SideDirection value="0" />
              <SideDirection value="0" />
              <Type value="20" />
              <Depth value="21.7" />
              <SideInclination value="0" />
              <ToolType value="0" />
              <IsHole value="0" />
            </Attributes>
            <Segment X1="0" Y1="0" X2="600" Y2="0" />
            <Segment X1="600" Y1="0" X2="600" Y2="300" />
            <Segment X1="600" Y1="300" X2="0" Y2="300" />
            <Segment X1="0" Y1="300" X2="0" Y2="0" />
          </Path>
        </Zone>
        <Path>
          <Attributes>
            <Extreme1 value="1" />
            <Extreme2 value="1" />
            <ExpModule value="1.9" />
            <ToolType value="0" />
            <ToolNumber value="1" />
            <ToolId value="170" />
            <OrgPolygon value="1" />
            <OrgSide value="1" />
            <CutIncl value="0" />
            <SideInclination value="0" />
            <ToolInclination value="0" />
            <SideDirection value="0" />
            <Type value="276" />
            <Depth value="21.7" />
            <IsHole value="0" />
          </Attributes>
          <Segment X1="-2.9" Y1="-1.9" X2="602.9" Y2="-1.9" />
        </Path>
        <Path>
          <Attributes>
            <Extreme1 value="1" />
            <Extreme2 value="1" />
            <ExpModule value="1.9" />
            <ToolType value="0" />
            <ToolNumber value="1" />
            <ToolId value="170" />
            <OrgPolygon value="1" />
            <OrgSide value="2" />
            <CutIncl value="0" />
            <SideInclination value="0" />
            <ToolInclination value="0" />
            <SideDirection value="0" />
            <Type value="276" />
            <Depth value="21.7" />
            <IsHole value="0" />
          </Attributes>
          <Segment X1="601.9" Y1="-2.9" X2="601.9" Y2="302.9" />
        </Path>
        <Path>
          <Attributes>
            <Extreme1 value="1" />
            <Extreme2 value="1" />
            <ExpModule value="1.9" />
            <ToolType value="0" />
            <ToolNumber value="1" />
            <ToolId value="170" />
            <OrgPolygon value="1" />
            <OrgSide value="3" />
            <CutIncl value="0" />
            <SideInclination value="0" />
            <ToolInclination value="0" />
            <SideDirection value="0" />
            <Type value="276" />
            <Depth value="21.7" />
            <IsHole value="0" />
          </Attributes>
          <Segment X1="602.9" Y1="301.9" X2="-2.9" Y2="301.9" />
        </Path>
        <Path>
          <Attributes>
            <Extreme1 value="1" />
            <Extreme2 value="1" />
            <ExpModule value="1.9" />
            <ToolType value="0" />
            <ToolNumber value="1" />
            <ToolId value="170" />
            <OrgPolygon value="1" />
            <OrgSide value="4" />
            <CutIncl value="0" />
            <SideInclination value="0" />
            <ToolInclination value="0" />
            <SideDirection value="0" />
            <Type value="276" />
            <Depth value="21.7" />
            <IsHole value="0" />
          </Attributes>
          <Segment X1="-1.9" Y1="302.9" X2="-1.9" Y2="-2.9" />
        </Path>
      </Piece>
    </Group>
    <Group Id="385713" Code="GR_0117">
      <Piece Id="662615" Code="_SP00023518_595" Type="0">
        <Zone>
          <MatrixRT m00="1" m01="0" m02="1879.79952347826" m10="0" m11="1" m12="61.216397625416" m20="0" m21="0" m22="1" />
          <Path>
            <Attributes>
              <SideDirection value="0" />
              <SideDirection value="0" />
              <SideDirection value="0" />
              <SideDirection value="0" />
              <Type value="20" />
              <Depth value="21.7" />
              <SideInclination value="0" />
              <ToolType value="0" />
              <IsHole value="0" />
            </Attributes>
            <Segment X1="0" Y1="0" X2="600" Y2="0" />
            <Segment X1="600" Y1="0" X2="600" Y2="300" />
            <Segment X1="600" Y1="300" X2="0" Y2="300" />
            <Segment X1="0" Y1="300" X2="0" Y2="0" />
          </Path>
        </Zone>
        <Path>
          <Attributes>
            <Extreme1 value="1" />
            <Extreme2 value="1" />
            <ExpModule value="1.9" />
            <ToolType value="0" />
            <ToolNumber value="1" />
            <ToolId value="170" />
            <OrgPolygon value="1" />
            <OrgSide value="1" />
            <CutIncl value="0" />
            <SideInclination value="0" />
            <ToolInclination value="0" />
            <SideDirection value="0" />
            <Type value="276" />
            <Depth value="21.7" />
            <IsHole value="0" />
          </Attributes>
          <Segment X1="-2.9" Y1="-1.9" X2="602.9" Y2="-1.9" />
        </Path>
        <Path>
          <Attributes>
            <Extreme1 value="1" />
            <Extreme2 value="1" />
            <ExpModule value="1.9" />
            <ToolType value="0" />
            <ToolNumber value="1" />
            <ToolId value="170" />
            <OrgPolygon value="1" />
            <OrgSide value="2" />
            <CutIncl value="0" />
            <SideInclination value="0" />
            <ToolInclination value="0" />
            <SideDirection value="0" />
            <Type value="276" />
            <Depth value="21.7" />
            <IsHole value="0" />
          </Attributes>
          <Segment X1="601.9" Y1="-2.9" X2="601.9" Y2="302.9" />
        </Path>
        <Path>
          <Attributes>
            <Extreme1 value="1" />
            <Extreme2 value="1" />
            <ExpModule value="1.9" />
            <ToolType value="0" />
            <ToolNumber value="1" />
            <ToolId value="170" />
            <OrgPolygon value="1" />
            <OrgSide value="3" />
            <CutIncl value="0" />
            <SideInclination value="0" />
            <ToolInclination value="0" />
            <SideDirection value="0" />
            <Type value="276" />
            <Depth value="21.7" />
            <IsHole value="0" />
          </Attributes>
          <Segment X1="602.9" Y1="301.9" X2="-2.9" Y2="301.9" />
        </Path>
        <Path>
          <Attributes>
            <Extreme1 value="1" />
            <Extreme2 value="1" />
            <ExpModule value="1.9" />
            <ToolType value="0" />
            <ToolNumber value="1" />
            <ToolId value="170" />
            <OrgPolygon value="1" />
            <OrgSide value="4" />
            <CutIncl value="0" />
            <SideInclination value="0" />
            <ToolInclination value="0" />
            <SideDirection value="0" />
            <Type value="276" />
            <Depth value="21.7" />
            <IsHole value="0" />
          </Attributes>
          <Segment X1="-1.9" Y1="302.9" X2="-1.9" Y2="-2.9" />
        </Path>
      </Piece>
    </Group>
    <Group Id="385714" Code="GR_0118">
      <Piece Id="662616" Code="_SP00023518_596" Type="0">
        <Zone>
          <MatrixRT m00="1" m01="0" m02="1275.99952347826" m10="0" m11="1" m12="61.2163976254161" m20="0" m21="0" m22="1" />
          <Path>
            <Attributes>
              <SideDirection value="0" />
              <SideDirection value="0" />
              <SideDirection value="0" />
              <SideDirection value="0" />
              <Type value="20" />
              <Depth value="21.7" />
              <SideInclination value="0" />
              <ToolType value="0" />
              <IsHole value="0" />
            </Attributes>
            <Segment X1="0" Y1="0" X2="600" Y2="0" />
            <Segment X1="600" Y1="0" X2="600" Y2="300" />
            <Segment X1="600" Y1="300" X2="0" Y2="300" />
            <Segment X1="0" Y1="300" X2="0" Y2="0" />
          </Path>
        </Zone>
        <Path>
          <Attributes>
            <Extreme1 value="1" />
            <Extreme2 value="1" />
            <ExpModule value="1.9" />
            <ToolType value="0" />
            <ToolNumber value="1" />
            <ToolId value="170" />
            <OrgPolygon value="1" />
            <OrgSide value="1" />
            <CutIncl value="0" />
            <SideInclination value="0" />
            <ToolInclination value="0" />
            <SideDirection value="0" />
            <Type value="276" />
            <Depth value="21.7" />
            <IsHole value="0" />
          </Attributes>
          <Segment X1="-2.9" Y1="-1.9" X2="602.9" Y2="-1.9" />
        </Path>
        <Path>
          <Attributes>
            <Extreme1 value="1" />
            <Extreme2 value="1" />
            <ExpModule value="1.9" />
            <ToolType value="0" />
            <ToolNumber value="1" />
            <ToolId value="170" />
            <OrgPolygon value="1" />
            <OrgSide value="2" />
            <CutIncl value="0" />
            <SideInclination value="0" />
            <ToolInclination value="0" />
            <SideDirection value="0" />
            <Type value="276" />
            <Depth value="21.7" />
            <IsHole value="0" />
          </Attributes>
          <Segment X1="601.9" Y1="-2.9" X2="601.9" Y2="302.9" />
        </Path>
        <Path>
          <Attributes>
            <Extreme1 value="1" />
            <Extreme2 value="1" />
            <ExpModule value="1.9" />
            <ToolType value="0" />
            <ToolNumber value="1" />
            <ToolId value="170" />
            <OrgPolygon value="1" />
            <OrgSide value="3" />
            <CutIncl value="0" />
            <SideInclination value="0" />
            <ToolInclination value="0" />
            <SideDirection value="0" />
            <Type value="276" />
            <Depth value="21.7" />
            <IsHole value="0" />
          </Attributes>
          <Segment X1="602.9" Y1="301.9" X2="-2.9" Y2="301.9" />
        </Path>
        <Path>
          <Attributes>
            <Extreme1 value="1" />
            <Extreme2 value="1" />
            <ExpModule value="1.9" />
            <ToolType value="0" />
            <ToolNumber value="1" />
            <ToolId value="170" />
            <OrgPolygon value="1" />
            <OrgSide value="4" />
            <CutIncl value="0" />
            <SideInclination value="0" />
            <ToolInclination value="0" />
            <SideDirection value="0" />
            <Type value="276" />
            <Depth value="21.7" />
            <IsHole value="0" />
          </Attributes>
          <Segment X1="-1.9" Y1="302.9" X2="-1.9" Y2="-2.9" />
        </Path>
      </Piece>
    </Group>
    <Group Id="385715" Code="GR_0119">
      <Piece Id="662617" Code="_SP00023518_597" Type="0">
        <Zone>
          <MatrixRT m00="1" m01="0" m02="672.199523478262" m10="0" m11="1" m12="61.216397625416" m20="0" m21="0" m22="1" />
          <Path>
            <Attributes>
              <SideDirection value="0" />
              <SideDirection value="0" />
              <SideDirection value="0" />
              <SideDirection value="0" />
              <Type value="20" />
              <Depth value="21.7" />
              <SideInclination value="0" />
              <ToolType value="0" />
              <IsHole value="0" />
            </Attributes>
            <Segment X1="0" Y1="0" X2="600" Y2="0" />
            <Segment X1="600" Y1="0" X2="600" Y2="300" />
            <Segment X1="600" Y1="300" X2="0" Y2="300" />
            <Segment X1="0" Y1="300" X2="0" Y2="0" />
          </Path>
        </Zone>
        <Path>
          <Attributes>
            <Extreme1 value="1" />
            <Extreme2 value="1" />
            <ExpModule value="1.9" />
            <ToolType value="0" />
            <ToolNumber value="1" />
            <ToolId value="170" />
            <OrgPolygon value="1" />
            <OrgSide value="1" />
            <CutIncl value="0" />
            <SideInclination value="0" />
            <ToolInclination value="0" />
            <SideDirection value="0" />
            <Type value="276" />
            <Depth value="21.7" />
            <IsHole value="0" />
          </Attributes>
          <Segment X1="-2.9" Y1="-1.9" X2="602.9" Y2="-1.9" />
        </Path>
        <Path>
          <Attributes>
            <Extreme1 value="1" />
            <Extreme2 value="1" />
            <ExpModule value="1.9" />
            <ToolType value="0" />
            <ToolNumber value="1" />
            <ToolId value="170" />
            <OrgPolygon value="1" />
            <OrgSide value="2" />
            <CutIncl value="0" />
            <SideInclination value="0" />
            <ToolInclination value="0" />
            <SideDirection value="0" />
            <Type value="276" />
            <Depth value="21.7" />
            <IsHole value="0" />
          </Attributes>
          <Segment X1="601.9" Y1="-2.9" X2="601.9" Y2="302.9" />
        </Path>
        <Path>
          <Attributes>
            <Extreme1 value="1" />
            <Extreme2 value="1" />
            <ExpModule value="1.9" />
            <ToolType value="0" />
            <ToolNumber value="1" />
            <ToolId value="170" />
            <OrgPolygon value="1" />
            <OrgSide value="3" />
            <CutIncl value="0" />
            <SideInclination value="0" />
            <ToolInclination value="0" />
            <SideDirection value="0" />
            <Type value="276" />
            <Depth value="21.7" />
            <IsHole value="0" />
          </Attributes>
          <Segment X1="602.9" Y1="301.9" X2="-2.9" Y2="301.9" />
        </Path>
        <Path>
          <Attributes>
            <Extreme1 value="1" />
            <Extreme2 value="1" />
            <ExpModule value="1.9" />
            <ToolType value="0" />
            <ToolNumber value="1" />
            <ToolId value="170" />
            <OrgPolygon value="1" />
            <OrgSide value="4" />
            <CutIncl value="0" />
            <SideInclination value="0" />
            <ToolInclination value="0" />
            <SideDirection value="0" />
            <Type value="276" />
            <Depth value="21.7" />
            <IsHole value="0" />
          </Attributes>
          <Segment X1="-1.9" Y1="302.9" X2="-1.9" Y2="-2.9" />
        </Path>
      </Piece>
    </Group>
    <Group Id="385716" Code="GR_0120">
      <Piece Id="662618" Code="_SP00023517_598" Type="0">
        <Zone>
          <MatrixRT m00="-3.49148336110938E-15" m01="-1" m02="739.085492994642" m10="1" m11="-3.49148336110938E-15" m12="514.627270094385" m20="0" m21="0" m22="1" />
          <Path>
            <Attributes>
              <SideDirection value="0" />
              <SideDirection value="0" />
              <SideDirection value="0" />
              <SideDirection value="0" />
              <Type value="20" />
              <Depth value="21.7" />
              <SideInclination value="0" />
              <ToolType value="0" />
              <IsHole value="0" />
            </Attributes>
            <Segment X1="0" Y1="0" X2="600" Y2="0" />
            <Segment X1="600" Y1="0" X2="600" Y2="400" />
            <Segment X1="600" Y1="400" X2="0" Y2="400" />
            <Segment X1="0" Y1="400" X2="0" Y2="0" />
          </Path>
        </Zone>
        <Path>
          <Attributes>
            <Extreme1 value="1" />
            <Extreme2 value="1" />
            <ExpModule value="1.9" />
            <ToolType value="0" />
            <ToolNumber value="1" />
            <ToolId value="170" />
            <OrgPolygon value="1" />
            <OrgSide value="1" />
            <CutIncl value="0" />
            <SideInclination value="0" />
            <ToolInclination value="0" />
            <SideDirection value="0" />
            <Type value="276" />
            <Depth value="21.7" />
            <IsHole value="0" />
          </Attributes>
          <Segment X1="-2.9" Y1="-1.9" X2="602.9" Y2="-1.9" />
        </Path>
        <Path>
          <Attributes>
            <Extreme1 value="1" />
            <Extreme2 value="1" />
            <ExpModule value="1.9" />
            <ToolType value="0" />
            <ToolNumber value="1" />
            <ToolId value="170" />
            <OrgPolygon value="1" />
            <OrgSide value="2" />
            <CutIncl value="0" />
            <SideInclination value="0" />
            <ToolInclination value="0" />
            <SideDirection value="0" />
            <Type value="276" />
            <Depth value="21.7" />
            <IsHole value="0" />
          </Attributes>
          <Segment X1="601.9" Y1="-2.9" X2="601.9" Y2="402.9" />
        </Path>
        <Path>
          <Attributes>
            <Extreme1 value="1" />
            <Extreme2 value="1" />
            <ExpModule value="1.9" />
            <ToolType value="0" />
            <ToolNumber value="1" />
            <ToolId value="170" />
            <OrgPolygon value="1" />
            <OrgSide value="3" />
            <CutIncl value="0" />
            <SideInclination value="0" />
            <ToolInclination value="0" />
            <SideDirection value="0" />
            <Type value="276" />
            <Depth value="21.7" />
            <IsHole value="0" />
          </Attributes>
          <Segment X1="602.9" Y1="401.9" X2="-2.9" Y2="401.9" />
        </Path>
        <Path>
          <Attributes>
            <Extreme1 value="1" />
            <Extreme2 value="1" />
            <ExpModule value="1.9" />
            <ToolType value="0" />
            <ToolNumber value="1" />
            <ToolId value="170" />
            <OrgPolygon value="1" />
            <OrgSide value="4" />
            <CutIncl value="0" />
            <SideInclination value="0" />
            <ToolInclination value="0" />
            <SideDirection value="0" />
            <Type value="276" />
            <Depth value="21.7" />
            <IsHole value="0" />
          </Attributes>
          <Segment X1="-1.9" Y1="402.9" X2="-1.9" Y2="-2.9" />
        </Path>
      </Piece>
    </Group>
  </Slab>
</CUT_SCHEME>