<?xml version="1.0" encoding="UTF-8"?>
<CUT_SCHEME>
  <Versions BretonTouch="1.32.0+767" XmlCam3="1.2.1.0" Aom3.API="4.21.1.0" CSE="1.32.0+767" CUT_SCHEME_VERSION="3.0.0.0" />
  <CutSchemeGuid SLAB00000000041945="2b6570d0-eb14-419a-94f4-54ba102582e3">
    <T_PARAMETERS Guid="33082151-0000-0000-0000-000000000000" />
  </CutSchemeGuid>
  <Slab Id="148138" Code="SLAB00000000041945" Length="2972.85815429688" Width="1581.50451660156" Thickness="20" ThicknessId="548" MaterialId="889">
    <Tool IdTool="166">
      <DiskDiameter>408.499</DiskDiameter>
      <DiskThickness>4</DiskThickness>
      <DiskGroove>92.6162556536775</DiskGroove>
    </Tool>
    <Zone>
      <Attributes />
      <MatrixRT m00="1" m01="0" m02="99.99999974089" m10="0" m11="1" m12="35.0735034316796" m20="0" m21="0" m22="1" />
      <Path Type="" Mode="EN_PATH_MODE_UNKNOW">
        <Attributes>
          <__INTERNAL_NAME_ value="INST_4010781" />
        </Attributes>
        <Segment X1="0" Y1="0" X2="2611.27313895994" Y2="2.98427949019242E-13" />
        <Segment X1="2611.27313895994" Y1="2.98427949019242E-13" X2="2817.49610001304" Y2="143.093483179703" />
        <Segment X1="2817.49610001304" Y1="143.093483179703" X2="2972.85808695652" Y2="655.586271279003" />
        <Segment X1="2972.85808695652" Y1="655.586271279003" X2="2972.85808695652" Y2="903.360527354758" />
        <Segment X1="2972.85808695652" Y1="903.360527354758" X2="2773.07547258003" Y2="1547.10450701233" />
        <Segment X1="2773.07547258003" Y1="1547.10450701233" X2="1890.45549796119" Y2="1505.56944938321" />
        <Segment X1="1890.45549796119" Y1="1505.56944938321" X2="1400.67428056988" Y2="1581.50452184698" />
        <Segment X1="1400.67428056988" Y1="1581.50452184698" X2="694.478106656835" Y2="1535.94347836872" />
        <Segment X1="694.478106656835" Y1="1535.94347836872" X2="259.174245697985" Y2="1574.5418502764" />
        <Segment X1="259.174245697985" Y1="1574.5418502764" X2="0" Y2="1427.87735464886" />
        <Segment X1="0" Y1="1427.87735464886" X2="0" Y2="0" />
      </Path>
    </Zone>
    <Group Id="344070" Code="GR_0788">
      <Piece Id="612163" Code="_SP00019893_2917" Type="0">
        <Zone>
          <MatrixRT m00="-3.49148336110938E-15" m01="-1" m02="2773.1884057971" m10="1" m11="-3.49148336110938E-15" m12="149.405797101449" m20="0" m21="0" m22="1" />
          <Path>
            <Attributes>
              <SideDirection value="0" />
              <SideDirection value="0" />
              <SideDirection value="0" />
              <SideDirection value="0" />
              <Type value="20" />
              <Depth value="21.7" />
              <SideInclination value="0" />
              <ToolType value="0" />
              <IsHole value="0" />
            </Attributes>
            <Segment X1="0" Y1="0" X2="1200" Y2="0" />
            <Segment X1="1200" Y1="0" X2="1200" Y2="800" />
            <Segment X1="1200" Y1="800" X2="0" Y2="800" />
            <Segment X1="0" Y1="800" X2="0" Y2="0" />
          </Path>
        </Zone>
        <Path>
          <Attributes>
            <Extreme1 value="1" />
            <Extreme2 value="1" />
            <ExpModule value="2" />
            <ToolType value="0" />
            <ToolNumber value="1" />
            <ToolId value="166" />
            <OrgPolygon value="1" />
            <OrgSide value="1" />
            <CutIncl value="0" />
            <SideInclination value="0" />
            <ToolInclination value="0" />
            <SideDirection value="0" />
            <Type value="276" />
            <Depth value="21.7" />
            <IsHole value="0" />
          </Attributes>
          <Segment X1="-3" Y1="-2" X2="1203" Y2="-2" />
        </Path>
        <Path>
          <Attributes>
            <Extreme1 value="1" />
            <Extreme2 value="1" />
            <ExpModule value="2" />
            <ToolType value="0" />
            <ToolNumber value="1" />
            <ToolId value="166" />
            <OrgPolygon value="1" />
            <OrgSide value="2" />
            <CutIncl value="0" />
            <SideInclination value="0" />
            <ToolInclination value="0" />
            <SideDirection value="0" />
            <Type value="276" />
            <Depth value="21.7" />
            <IsHole value="0" />
          </Attributes>
          <Segment X1="1202" Y1="-3" X2="1202" Y2="803" />
        </Path>
        <Path>
          <Attributes>
            <Extreme1 value="1" />
            <Extreme2 value="1" />
            <ExpModule value="2" />
            <ToolType value="0" />
            <ToolNumber value="1" />
            <ToolId value="166" />
            <OrgPolygon value="1" />
            <OrgSide value="3" />
            <CutIncl value="0" />
            <SideInclination value="0" />
            <ToolInclination value="0" />
            <SideDirection value="0" />
            <Type value="276" />
            <Depth value="21.7" />
            <IsHole value="0" />
          </Attributes>
          <Segment X1="1203" Y1="802" X2="-3" Y2="802" />
        </Path>
        <Path>
          <Attributes>
            <Extreme1 value="1" />
            <Extreme2 value="1" />
            <ExpModule value="2" />
            <ToolType value="0" />
            <ToolNumber value="1" />
            <ToolId value="166" />
            <OrgPolygon value="1" />
            <OrgSide value="4" />
            <CutIncl value="0" />
            <SideInclination value="0" />
            <ToolInclination value="0" />
            <SideDirection value="0" />
            <Type value="276" />
            <Depth value="21.7" />
            <IsHole value="0" />
          </Attributes>
          <Segment X1="-2" Y1="803" X2="-2" Y2="-3" />
        </Path>
      </Piece>
    </Group>
    <Group Id="344071" Code="GR_0789">
      <Piece Id="612164" Code="_SP00019893_2918" Type="0">
        <Zone>
          <MatrixRT m00="-3.49148336110938E-15" m01="-1" m02="1969.1884057971" m10="1" m11="-3.49148336110938E-15" m12="149.405797101449" m20="0" m21="0" m22="1" />
          <Path>
            <Attributes>
              <SideDirection value="0" />
              <SideDirection value="0" />
              <SideDirection value="0" />
              <SideDirection value="0" />
              <Type value="20" />
              <Depth value="21.7" />
              <SideInclination value="0" />
              <ToolType value="0" />
              <IsHole value="0" />
            </Attributes>
            <Segment X1="0" Y1="0" X2="1200" Y2="0" />
            <Segment X1="1200" Y1="0" X2="1200" Y2="800" />
            <Segment X1="1200" Y1="800" X2="0" Y2="800" />
            <Segment X1="0" Y1="800" X2="0" Y2="0" />
          </Path>
        </Zone>
        <Path>
          <Attributes>
            <Extreme1 value="1" />
            <Extreme2 value="1" />
            <ExpModule value="2" />
            <ToolType value="0" />
            <ToolNumber value="1" />
            <ToolId value="166" />
            <OrgPolygon value="1" />
            <OrgSide value="1" />
            <CutIncl value="0" />
            <SideInclination value="0" />
            <ToolInclination value="0" />
            <SideDirection value="0" />
            <Type value="276" />
            <Depth value="21.7" />
            <IsHole value="0" />
          </Attributes>
          <Segment X1="-3" Y1="-2" X2="1203" Y2="-2" />
        </Path>
        <Path>
          <Attributes>
            <Extreme1 value="1" />
            <Extreme2 value="1" />
            <ExpModule value="2" />
            <ToolType value="0" />
            <ToolNumber value="1" />
            <ToolId value="166" />
            <OrgPolygon value="1" />
            <OrgSide value="2" />
            <CutIncl value="0" />
            <SideInclination value="0" />
            <ToolInclination value="0" />
            <SideDirection value="0" />
            <Type value="276" />
            <Depth value="21.7" />
            <IsHole value="0" />
          </Attributes>
          <Segment X1="1202" Y1="-3" X2="1202" Y2="803" />
        </Path>
        <Path>
          <Attributes>
            <Extreme1 value="1" />
            <Extreme2 value="1" />
            <ExpModule value="2" />
            <ToolType value="0" />
            <ToolNumber value="1" />
            <ToolId value="166" />
            <OrgPolygon value="1" />
            <OrgSide value="3" />
            <CutIncl value="0" />
            <SideInclination value="0" />
            <ToolInclination value="0" />
            <SideDirection value="0" />
            <Type value="276" />
            <Depth value="21.7" />
            <IsHole value="0" />
          </Attributes>
          <Segment X1="1203" Y1="802" X2="-3" Y2="802" />
        </Path>
        <Path>
          <Attributes>
            <Extreme1 value="1" />
            <Extreme2 value="1" />
            <ExpModule value="2" />
            <ToolType value="0" />
            <ToolNumber value="1" />
            <ToolId value="166" />
            <OrgPolygon value="1" />
            <OrgSide value="4" />
            <CutIncl value="0" />
            <SideInclination value="0" />
            <ToolInclination value="0" />
            <SideDirection value="0" />
            <Type value="276" />
            <Depth value="21.7" />
            <IsHole value="0" />
          </Attributes>
          <Segment X1="-2" Y1="803" X2="-2" Y2="-3" />
        </Path>
      </Piece>
    </Group>
    <Group Id="344072" Code="GR_0790">
      <Piece Id="612165" Code="_SP00019893_2919" Type="0">
        <Zone>
          <MatrixRT m00="-3.49148336110938E-15" m01="-1" m02="1165.1884057971" m10="1" m11="-3.49148336110938E-15" m12="149.405797101449" m20="0" m21="0" m22="1" />
          <Path>
            <Attributes>
              <SideDirection value="0" />
              <SideDirection value="0" />
              <SideDirection value="0" />
              <SideDirection value="0" />
              <Type value="20" />
              <Depth value="21.7" />
              <SideInclination value="0" />
              <ToolType value="0" />
              <IsHole value="0" />
            </Attributes>
            <Segment X1="0" Y1="0" X2="1200" Y2="0" />
            <Segment X1="1200" Y1="0" X2="1200" Y2="800" />
            <Segment X1="1200" Y1="800" X2="0" Y2="800" />
            <Segment X1="0" Y1="800" X2="0" Y2="0" />
          </Path>
        </Zone>
        <Path>
          <Attributes>
            <Extreme1 value="1" />
            <Extreme2 value="1" />
            <ExpModule value="2" />
            <ToolType value="0" />
            <ToolNumber value="1" />
            <ToolId value="166" />
            <OrgPolygon value="1" />
            <OrgSide value="1" />
            <CutIncl value="0" />
            <SideInclination value="0" />
            <ToolInclination value="0" />
            <SideDirection value="0" />
            <Type value="276" />
            <Depth value="21.7" />
            <IsHole value="0" />
          </Attributes>
          <Segment X1="-3" Y1="-2" X2="1203" Y2="-2" />
        </Path>
        <Path>
          <Attributes>
            <Extreme1 value="1" />
            <Extreme2 value="1" />
            <ExpModule value="2" />
            <ToolType value="0" />
            <ToolNumber value="1" />
            <ToolId value="166" />
            <OrgPolygon value="1" />
            <OrgSide value="2" />
            <CutIncl value="0" />
            <SideInclination value="0" />
            <ToolInclination value="0" />
            <SideDirection value="0" />
            <Type value="276" />
            <Depth value="21.7" />
            <IsHole value="0" />
          </Attributes>
          <Segment X1="1202" Y1="-3" X2="1202" Y2="803" />
        </Path>
        <Path>
          <Attributes>
            <Extreme1 value="1" />
            <Extreme2 value="1" />
            <ExpModule value="2" />
            <ToolType value="0" />
            <ToolNumber value="1" />
            <ToolId value="166" />
            <OrgPolygon value="1" />
            <OrgSide value="3" />
            <CutIncl value="0" />
            <SideInclination value="0" />
            <ToolInclination value="0" />
            <SideDirection value="0" />
            <Type value="276" />
            <Depth value="21.7" />
            <IsHole value="0" />
          </Attributes>
          <Segment X1="1203" Y1="802" X2="-3" Y2="802" />
        </Path>
        <Path>
          <Attributes>
            <Extreme1 value="1" />
            <Extreme2 value="1" />
            <ExpModule value="2" />
            <ToolType value="0" />
            <ToolNumber value="1" />
            <ToolId value="166" />
            <OrgPolygon value="1" />
            <OrgSide value="4" />
            <CutIncl value="0" />
            <SideInclination value="0" />
            <ToolInclination value="0" />
            <SideDirection value="0" />
            <Type value="276" />
            <Depth value="21.7" />
            <IsHole value="0" />
          </Attributes>
          <Segment X1="-2" Y1="803" X2="-2" Y2="-3" />
        </Path>
      </Piece>
    </Group>
    <Group Id="344073" Code="GR_0791">
      <Piece Id="612166" Code="_SP00019895_2920" Type="0">
        <Zone>
          <MatrixRT m00="-3.49148336110938E-15" m01="-1" m02="212.188405797101" m10="1" m11="-3.49148336110938E-15" m12="149.405797101449" m20="0" m21="0" m22="1" />
          <Path>
            <Attributes>
              <SideDirection value="0" />
              <SideDirection value="0" />
              <SideDirection value="0" />
              <SideDirection value="0" />
              <Type value="20" />
              <Depth value="21.7" />
              <SideInclination value="0" />
              <ToolType value="0" />
              <IsHole value="0" />
            </Attributes>
            <Segment X1="0" Y1="0" X2="1200" Y2="0" />
            <Segment X1="1200" Y1="0" X2="1200" Y2="145" />
            <Segment X1="1200" Y1="145" X2="0" Y2="145" />
            <Segment X1="0" Y1="145" X2="0" Y2="0" />
          </Path>
        </Zone>
        <Path>
          <Attributes>
            <Extreme1 value="1" />
            <Extreme2 value="1" />
            <ExpModule value="2" />
            <ToolType value="0" />
            <ToolNumber value="1" />
            <ToolId value="166" />
            <OrgPolygon value="1" />
            <OrgSide value="1" />
            <CutIncl value="0" />
            <SideInclination value="0" />
            <ToolInclination value="0" />
            <SideDirection value="0" />
            <Type value="276" />
            <Depth value="21.7" />
            <IsHole value="0" />
          </Attributes>
          <Segment X1="-3" Y1="-2" X2="1203" Y2="-2" />
        </Path>
        <Path>
          <Attributes>
            <Extreme1 value="1" />
            <Extreme2 value="1" />
            <ExpModule value="2" />
            <ToolType value="0" />
            <ToolNumber value="1" />
            <ToolId value="166" />
            <OrgPolygon value="1" />
            <OrgSide value="2" />
            <CutIncl value="0" />
            <SideInclination value="0" />
            <ToolInclination value="0" />
            <SideDirection value="0" />
            <Type value="276" />
            <Depth value="21.7" />
            <IsHole value="0" />
          </Attributes>
          <Segment X1="1202" Y1="-3" X2="1202" Y2="148" />
        </Path>
        <Path>
          <Attributes>
            <Extreme1 value="1" />
            <Extreme2 value="1" />
            <ExpModule value="2" />
            <ToolType value="0" />
            <ToolNumber value="1" />
            <ToolId value="166" />
            <OrgPolygon value="1" />
            <OrgSide value="3" />
            <CutIncl value="0" />
            <SideInclination value="0" />
            <ToolInclination value="0" />
            <SideDirection value="0" />
            <Type value="276" />
            <Depth value="21.7" />
            <IsHole value="0" />
          </Attributes>
          <Segment X1="1203" Y1="147" X2="-3" Y2="147" />
        </Path>
        <Path>
          <Attributes>
            <Extreme1 value="1" />
            <Extreme2 value="1" />
            <ExpModule value="2" />
            <ToolType value="0" />
            <ToolNumber value="1" />
            <ToolId value="166" />
            <OrgPolygon value="1" />
            <OrgSide value="4" />
            <CutIncl value="0" />
            <SideInclination value="0" />
            <ToolInclination value="0" />
            <SideDirection value="0" />
            <Type value="276" />
            <Depth value="21.7" />
            <IsHole value="0" />
          </Attributes>
          <Segment X1="-2" Y1="148" X2="-2" Y2="-3" />
        </Path>
      </Piece>
    </Group>
    <Group Id="344074" Code="GR_0792">
      <Piece Id="612167" Code="_SP00019895_2921" Type="0">
        <Zone>
          <MatrixRT m00="-3.49148336110938E-15" m01="-1" m02="361.188405797101" m10="1" m11="-3.49148336110938E-15" m12="149.405797101449" m20="0" m21="0" m22="1" />
          <Path>
            <Attributes>
              <SideDirection value="0" />
              <SideDirection value="0" />
              <SideDirection value="0" />
              <SideDirection value="0" />
              <Type value="20" />
              <Depth value="21.7" />
              <SideInclination value="0" />
              <ToolType value="0" />
              <IsHole value="0" />
            </Attributes>
            <Segment X1="0" Y1="0" X2="1200" Y2="0" />
            <Segment X1="1200" Y1="0" X2="1200" Y2="145" />
            <Segment X1="1200" Y1="145" X2="0" Y2="145" />
            <Segment X1="0" Y1="145" X2="0" Y2="0" />
          </Path>
        </Zone>
        <Path>
          <Attributes>
            <Extreme1 value="1" />
            <Extreme2 value="1" />
            <ExpModule value="2" />
            <ToolType value="0" />
            <ToolNumber value="1" />
            <ToolId value="166" />
            <OrgPolygon value="1" />
            <OrgSide value="1" />
            <CutIncl value="0" />
            <SideInclination value="0" />
            <ToolInclination value="0" />
            <SideDirection value="0" />
            <Type value="276" />
            <Depth value="21.7" />
            <IsHole value="0" />
          </Attributes>
          <Segment X1="-3" Y1="-2" X2="1203" Y2="-2" />
        </Path>
        <Path>
          <Attributes>
            <Extreme1 value="1" />
            <Extreme2 value="1" />
            <ExpModule value="2" />
            <ToolType value="0" />
            <ToolNumber value="1" />
            <ToolId value="166" />
            <OrgPolygon value="1" />
            <OrgSide value="2" />
            <CutIncl value="0" />
            <SideInclination value="0" />
            <ToolInclination value="0" />
            <SideDirection value="0" />
            <Type value="276" />
            <Depth value="21.7" />
            <IsHole value="0" />
          </Attributes>
          <Segment X1="1202" Y1="-3" X2="1202" Y2="148" />
        </Path>
        <Path>
          <Attributes>
            <Extreme1 value="1" />
            <Extreme2 value="1" />
            <ExpModule value="2" />
            <ToolType value="0" />
            <ToolNumber value="1" />
            <ToolId value="166" />
            <OrgPolygon value="1" />
            <OrgSide value="3" />
            <CutIncl value="0" />
            <SideInclination value="0" />
            <ToolInclination value="0" />
            <SideDirection value="0" />
            <Type value="276" />
            <Depth value="21.7" />
            <IsHole value="0" />
          </Attributes>
          <Segment X1="1203" Y1="147" X2="-3" Y2="147" />
        </Path>
        <Path>
          <Attributes>
            <Extreme1 value="1" />
            <Extreme2 value="1" />
            <ExpModule value="2" />
            <ToolType value="0" />
            <ToolNumber value="1" />
            <ToolId value="166" />
            <OrgPolygon value="1" />
            <OrgSide value="4" />
            <CutIncl value="0" />
            <SideInclination value="0" />
            <ToolInclination value="0" />
            <SideDirection value="0" />
            <Type value="276" />
            <Depth value="21.7" />
            <IsHole value="0" />
          </Attributes>
          <Segment X1="-2" Y1="148" X2="-2" Y2="-3" />
        </Path>
      </Piece>
    </Group>
  </Slab>
</CUT_SCHEME>